unitgrade2/__init__.py
unitgrade2/unitgrade2.py
unitgrade2/unitgrade_helpers2.py
unitgrade2/version.py
unitgrade_tuhe-0.0.1.dist-info/LICENSE
unitgrade_tuhe-0.0.1.dist-info/METADATA
unitgrade_tuhe-0.0.1.dist-info/WHEEL
unitgrade_tuhe-0.0.1.dist-info/top_level.txt
unitgrade_tuhe-0.0.1.dist-info/RECORD
