Metadata-Version: 2.1
Name: unitgrade-tuhe
Version: 0.0.1
Summary: A student homework/exam evaluation framework build on pythons unittest framework.
Home-page: https://lab.compute.dtu.dk/tuhe/unitgrade
Author: Tue Herlau
Author-email: tuhe@dtu.dk
License: UNKNOWN
Project-URL: Bug Tracker, https://lab.compute.dtu.dk/tuhe/unitgrade/issues
Platform: UNKNOWN
Classifier: Programming Language :: Python :: 3
Classifier: License :: OSI Approved :: MIT License
Classifier: Operating System :: OS Independent
Requires-Python: >=3.8
License-File: LICENSE
Requires-Dist: numpy
Requires-Dist: tabulate
Requires-Dist: tqdm
Requires-Dist: pyfiglet
Requires-Dist: colorama
Requires-Dist: coverage
